test_run_dir/PWM/PWM.PWMVerilatorTester349364187/PWM.v
module PWM(
  input        clock,
  input        reset,
  input  [3:0] io_rise,
  input  [3:0] io_fall,
  output       io_out
);
  reg [3:0] counter; // @[PWM.scala 15:30]
  reg [31:0] _RAND_0;
  reg  out; // @[PWM.scala 16:26]
  reg [31:0] _RAND_1;
  wire  _T_15; // @[PWM.scala 18:31]
  wire  _T_16; // @[PWM.scala 18:49]
  wire  _T_17; // @[PWM.scala 18:17]
  wire  _T_20; // @[PWM.scala 20:24]
  wire [4:0] _T_22; // @[PWM.scala 22:36]
  wire [3:0] _T_23; // @[PWM.scala 22:36]
  wire [3:0] _GEN_0; // @[PWM.scala 18:59]
  wire  _GEN_1; // @[PWM.scala 18:59]
  assign _T_15 = counter == io_rise; // @[PWM.scala 18:31]
  assign _T_16 = counter == io_fall; // @[PWM.scala 18:49]
  assign _T_17 = out ? _T_15 : _T_16; // @[PWM.scala 18:17]
  assign _T_20 = out == 1'h0; // @[PWM.scala 20:24]
  assign _T_22 = counter + 4'h1; // @[PWM.scala 22:36]
  assign _T_23 = counter + 4'h1; // @[PWM.scala 22:36]
  assign _GEN_0 = _T_17 ? 4'h1 : _T_23; // @[PWM.scala 18:59]
  assign _GEN_1 = _T_17 ? _T_20 : out; // @[PWM.scala 18:59]
  assign io_out = out; // @[PWM.scala 25:16]
`ifdef RANDOMIZE_GARBAGE_ASSIGN
`define RANDOMIZE
`endif
`ifdef RANDOMIZE_INVALID_ASSIGN
`define RANDOMIZE
`endif
`ifdef RANDOMIZE_REG_INIT
`define RANDOMIZE
`endif
`ifdef RANDOMIZE_MEM_INIT
`define RANDOMIZE
`endif
`ifndef RANDOM
`define RANDOM $random
`endif
`ifdef RANDOMIZE
  integer initvar;
  initial begin
    `ifdef INIT_RANDOM
      `INIT_RANDOM
    `endif
    `ifndef VERILATOR
      #0.002 begin end
    `endif
  `ifdef RANDOMIZE_REG_INIT
  _RAND_0 = {1{`RANDOM}};
  counter = _RAND_0[3:0];
  `endif // RANDOMIZE_REG_INIT
  `ifdef RANDOMIZE_REG_INIT
  _RAND_1 = {1{`RANDOM}};
  out = _RAND_1[0:0];
  `endif // RANDOMIZE_REG_INIT
  end
`endif // RANDOMIZE
  always @(posedge clock) begin
    if (reset) begin
      counter <= 4'h0;
    end else begin
      if (_T_17) begin
        counter <= 4'h1;
      end else begin
        counter <= _T_23;
      end
    end
    if (reset) begin
      out <= 1'h1;
    end else begin
      if (_T_17) begin
        out <= _T_20;
      end
    end
  end
endmodule

test_run_dir/PWM/PWM.PWMVerilatorTester349364187/PWM.vcd
$version Generated by VerilatedVcd $end
$date Thu Jun 27 14:53:52 2019
 $end
$timescale   1ns $end

 $scope module TOP $end
  $var wire  1 % clock $end
  $var wire  4 ( io_fall [3:0] $end
  $var wire  1 ) io_out $end
  $var wire  4 ' io_rise [3:0] $end
  $var wire  1 & reset $end
  $scope module PWM $end
   $var wire  1 % clock $end
   $var wire  4 # counter [3:0] $end
   $var wire  4 ( io_fall [3:0] $end
   $var wire  1 ) io_out $end
   $var wire  4 ' io_rise [3:0] $end
   $var wire  1 $ out $end
   $var wire  1 & reset $end
  $upscope $end
 $upscope $end
$enddefinitions $end


#0
b0000 #
0$
0%
1&
b0000 '
b0000 (
0)
#1
1$
1%
1)
#2
0%
#3
1%
#4
0%
#5
1%
#6
0%
#7
1%
#8
0%
#9
1%
#10
0%
0&
b1011 '
b0110 (
#11
b0001 #
1%
#12
0%
#13
b0010 #
1%
#14
0%
#15
b0011 #
1%
#16
0%
#17
b0100 #
1%
#18
0%
#19
b0101 #
1%
#20
0%
#21
b0110 #
1%
#22
0%
#23
b0111 #
1%
#24
0%
#25
b1000 #
1%
#26
0%
#27
b1001 #
1%
#28
0%
#29
b1010 #
1%
#30
0%
#31
b1011 #
1%
#32
0%
#33
b0001 #
0$
1%
0)
#34
0%
#35
b0010 #
1%
#36
0%
#37
b0011 #
1%
#38
0%
#39
b0100 #
1%
#40
0%
#41
b0101 #
1%
#42
0%
#43
b0110 #
1%
#44
0%
#45
b0001 #
1$
1%
1)
#46
0%
b0111 '
b1101 (
#47
b0010 #
1%
#48
0%
#49
b0011 #
1%
#50
0%
#51
b0100 #
1%
#52
0%
#53
b0101 #
1%
#54
0%
#55
b0110 #
1%
#56
0%
#57
b0111 #
1%
#58
0%
#59
b0001 #
0$
1%
0)
#60
0%
#61
b0010 #
1%
#62
0%
#63
b0011 #
1%
#64
0%
#65
b0100 #
1%
#66
0%
#67
b0101 #
1%
#68
0%
#69
b0110 #
1%
#70
0%
#71
b0111 #
1%
#72
0%
#73
b1000 #
1%
#74
0%
#75
b1001 #
1%
#76
0%
#77
b1010 #
1%
#78
0%
#79
b1011 #
1%
#80
0%
#81
b1100 #
1%
#82
0%
#83
b1101 #
1%
#84
0%
#85
b0001 #
1$
1%
1)
#86
0%
b1100 '
b1100 (
#87
b0010 #
1%
#88
0%
#89
b0011 #
1%
#90
0%
#91
b0100 #
1%
#92
0%
#93
b0101 #
1%
#94
0%
#95
b0110 #
1%
#96
0%
#97
b0111 #
1%
#98
0%
#99
b1000 #
1%
#100
0%
#101
b1001 #
1%
#102
0%
#103
b1010 #
1%
#104
0%
#105
b1011 #
1%
#106
0%
#107
b1100 #
1%
#108
0%
#109
b0001 #
0$
1%
0)
#110
0%
#111
b0010 #
1%
#112
0%
#113
b0011 #
1%
#114
0%
#115
b0100 #
1%
#116
0%
#117
b0101 #
1%
#118
0%
#119
b0110 #
1%
#120
0%
#121
b0111 #
1%
#122
0%
#123
b1000 #
1%
#124
0%
#125
b1001 #
1%
#126
0%
#127
b1010 #
1%
#128
0%
#129
b1011 #
1%
#130
0%
#131
b1100 #
1%
#132
0%
#133
b0001 #
1$
1%
1)
