test_run_dir/PWM/PWM.PWMVerilatorTester349364187/PWM.v
module PWM(
  input        clock,
  input        reset,
  input  [3:0] io_rise,
  input  [3:0] io_fall,
  output       io_out
);
  reg [3:0] counter; // @[PWM.scala 15:30]
  reg [31:0] _RAND_0;
  reg  out; // @[PWM.scala 16:26]
  reg [31:0] _RAND_1;
  wire  _T_15; // @[PWM.scala 18:31]
  wire  _T_16; // @[PWM.scala 18:49]
  wire  _T_17; // @[PWM.scala 18:17]
  wire  _T_20; // @[PWM.scala 20:24]
  wire [4:0] _T_22; // @[PWM.scala 22:36]
  wire [3:0] _T_23; // @[PWM.scala 22:36]
  wire [3:0] _GEN_0; // @[PWM.scala 18:59]
  wire  _GEN_1; // @[PWM.scala 18:59]
  assign _T_15 = counter == io_rise; // @[PWM.scala 18:31]
  assign _T_16 = counter == io_fall; // @[PWM.scala 18:49]
  assign _T_17 = out ? _T_15 : _T_16; // @[PWM.scala 18:17]
  assign _T_20 = out == 1'h0; // @[PWM.scala 20:24]
  assign _T_22 = counter + 4'h1; // @[PWM.scala 22:36]
  assign _T_23 = counter + 4'h1; // @[PWM.scala 22:36]
  assign _GEN_0 = _T_17 ? 4'h1 : _T_23; // @[PWM.scala 18:59]
  assign _GEN_1 = _T_17 ? _T_20 : out; // @[PWM.scala 18:59]
  assign io_out = out; // @[PWM.scala 25:16]
`ifdef RANDOMIZE_GARBAGE_ASSIGN
`define RANDOMIZE
`endif
`ifdef RANDOMIZE_INVALID_ASSIGN
`define RANDOMIZE
`endif
`ifdef RANDOMIZE_REG_INIT
`define RANDOMIZE
`endif
`ifdef RANDOMIZE_MEM_INIT
`define RANDOMIZE
`endif
`ifndef RANDOM
`define RANDOM $random
`endif
`ifdef RANDOMIZE
  integer initvar;
  initial begin
    `ifdef INIT_RANDOM
      `INIT_RANDOM
    `endif
    `ifndef VERILATOR
      #0.002 begin end
    `endif
  `ifdef RANDOMIZE_REG_INIT
  _RAND_0 = {1{`RANDOM}};
  counter = _RAND_0[3:0];
  `endif // RANDOMIZE_REG_INIT
  `ifdef RANDOMIZE_REG_INIT
  _RAND_1 = {1{`RANDOM}};
  out = _RAND_1[0:0];
  `endif // RANDOMIZE_REG_INIT
  end
`endif // RANDOMIZE
  always @(posedge clock) begin
    if (reset) begin
      counter <= 4'h0;
    end else begin
      if (_T_17) begin
        counter <= 4'h1;
      end else begin
        counter <= _T_23;
      end
    end
    if (reset) begin
      out <= 1'h1;
    end else begin
      if (_T_17) begin
        out <= _T_20;
      end
    end
  end
endmodule

test_run_dir/PWM/PWM.PWMFirrtlTester979600927/PWM.vcd
$date
2019-06-27T09:26+0000
$end
$version
0.2
$end
$comment

$end
$timescale 1ps  $end
$scope module PWM $end
 $var wire 1 ! io_out $end
 $var wire 4 " counter $end
 $var wire 1 # clock $end
 $var wire 1 $ out $end
 $var wire 4 % io_fall $end
 $var wire 4 & io_rise $end
 $var wire 1 ' reset $end
$upscope $end
$enddefinitions $end
$dumpvars
0#
x'
x$
bxxxx %
bxxxx "
bxxxx &
x!
$end
#0
1'
#1
1$
1!
1#
b0000 "
#2
0#
#3
1#
#4
0#
#5
1#
#6
0#
#7
1#
#8
0#
#9
1#
#10
b0001 &
0#
0'
b0101 %
#11
b0001 "
1#
#12
0#
#13
0$
1#
0!
#14
0#
#15
b0010 "
1#
#16
0#
#17
b0011 "
1#
#18
0#
#19
1#
b0100 "
#20
0#
#21
b0101 "
1#
#22
0#
#23
b0001 "
1$
1!
1#
#24
b1100 %
b0110 &
0#
#25
b0010 "
1#
#26
0#
#27
b0011 "
1#
#28
0#
#29
1#
b0100 "
#30
0#
#31
b0101 "
1#
#32
0#
#33
1#
b0110 "
#34
0#
#35
b0001 "
0$
1#
0!
#36
0#
#37
b0010 "
1#
#38
0#
#39
b0011 "
1#
#40
0#
#41
1#
b0100 "
#42
0#
#43
b0101 "
1#
#44
0#
#45
1#
b0110 "
#46
0#
#47
b0111 "
1#
#48
0#
#49
1#
b1000 "
#50
0#
#51
b1001 "
1#
#52
0#
#53
b1010 "
1#
#54
0#
#55
b1011 "
1#
#56
0#
#57
b1100 "
1#
#58
0#
#59
b0001 "
1$
1!
1#
#60
b0110 %
0#
b1101 &
#61
b0010 "
1#
#62
0#
#63
b0011 "
1#
#64
0#
#65
1#
b0100 "
#66
0#
#67
b0101 "
1#
#68
0#
#69
1#
b0110 "
#70
0#
#71
b0111 "
1#
#72
0#
#73
1#
b1000 "
#74
0#
#75
b1001 "
1#
#76
0#
#77
b1010 "
1#
#78
0#
#79
b1011 "
1#
#80
0#
#81
b1100 "
1#
#82
0#
#83
b1101 "
1#
#84
0#
#85
b0001 "
0$
1#
0!
#86
0#
#87
b0010 "
1#
#88
0#
#89
b0011 "
1#
#90
0#
#91
1#
b0100 "
#92
0#
#93
b0101 "
1#
#94
0#
#95
1#
b0110 "
#96
0#
#97
b0001 "
1$
1!
1#
