test_run_dir/PWM.PWMTOMTester973488291/PWM.v
module PWM(
  input        clock,
  input        reset,
  input  [1:0] io_rise,
  input  [1:0] io_fall,
  output       io_out
);
  reg [1:0] counter; // @[PWM.scala 15:30]
  reg [31:0] _RAND_0;
  reg  out; // @[PWM.scala 16:26]
  reg [31:0] _RAND_1;
  wire  _T_15; // @[PWM.scala 18:31]
  wire  _T_16; // @[PWM.scala 18:49]
  wire  _T_17; // @[PWM.scala 18:17]
  wire  _T_20; // @[PWM.scala 20:24]
  wire [2:0] _T_22; // @[PWM.scala 22:36]
  wire [1:0] _T_23; // @[PWM.scala 22:36]
  wire [1:0] _GEN_0; // @[PWM.scala 18:59]
  wire  _GEN_1; // @[PWM.scala 18:59]
  assign _T_15 = counter == io_rise; // @[PWM.scala 18:31]
  assign _T_16 = counter == io_fall; // @[PWM.scala 18:49]
  assign _T_17 = out ? _T_15 : _T_16; // @[PWM.scala 18:17]
  assign _T_20 = out == 1'h0; // @[PWM.scala 20:24]
  assign _T_22 = counter + 2'h1; // @[PWM.scala 22:36]
  assign _T_23 = counter + 2'h1; // @[PWM.scala 22:36]
  assign _GEN_0 = _T_17 ? 2'h1 : _T_23; // @[PWM.scala 18:59]
  assign _GEN_1 = _T_17 ? _T_20 : out; // @[PWM.scala 18:59]
  assign io_out = out; // @[PWM.scala 25:16]
`ifdef RANDOMIZE_GARBAGE_ASSIGN
`define RANDOMIZE
`endif
`ifdef RANDOMIZE_INVALID_ASSIGN
`define RANDOMIZE
`endif
`ifdef RANDOMIZE_REG_INIT
`define RANDOMIZE
`endif
`ifdef RANDOMIZE_MEM_INIT
`define RANDOMIZE
`endif
`ifndef RANDOM
`define RANDOM $random
`endif
`ifdef RANDOMIZE
  integer initvar;
  initial begin
    `ifdef INIT_RANDOM
      `INIT_RANDOM
    `endif
    `ifndef VERILATOR
      #0.002 begin end
    `endif
  `ifdef RANDOMIZE_REG_INIT
  _RAND_0 = {1{`RANDOM}};
  counter = _RAND_0[1:0];
  `endif // RANDOMIZE_REG_INIT
  `ifdef RANDOMIZE_REG_INIT
  _RAND_1 = {1{`RANDOM}};
  out = _RAND_1[0:0];
  `endif // RANDOMIZE_REG_INIT
  end
`endif // RANDOMIZE
  always @(posedge clock) begin
    if (reset) begin
      counter <= 2'h0;
    end else begin
      if (_T_17) begin
        counter <= 2'h1;
      end else begin
        counter <= _T_23;
      end
    end
    if (reset) begin
      out <= 1'h1;
    end else begin
      if (_T_17) begin
        out <= _T_20;
      end
    end
  end
endmodule

test_run_dir/PWM.PWMTOMTester973488291/PWM.vcd
$date
2019-06-27T09:32+0000
$end
$version
0.2
$end
$comment

$end
$timescale 1ps  $end
$scope module PWM $end
 $var wire 1 ! io_out $end
 $var wire 2 " counter $end
 $var wire 1 # clock $end
 $var wire 1 $ out $end
 $var wire 2 % io_fall $end
 $var wire 2 & io_rise $end
 $var wire 1 ' reset $end
$upscope $end
$enddefinitions $end
$dumpvars
0#
bxx %
x'
x$
bxx &
bxx "
x!
$end
#1
b00 "
1#
#2
0#
#3
1#
#4
0#
#5
1#
#6
0#
#7
1#
#8
0#
#9
1#
#10
0#
b10 &
b10 %
0'
#11
1#
b01 "
#12
0#
#13
1#
b10 "
#14
0#
#15
1#
b01 "
0$
0!
#16
0#
#17
1#
b10 "
#18
0#
#19
1$
1#
b01 "
1!
#20
b11 %
0#
b11 &
#21
1#
b10 "
#22
0#
#23
b11 "
1#
#24
0#
#25
1#
b01 "
0$
0!
#26
0#
#27
1#
b10 "
#28
0#
#29
b11 "
1#
#30
0#
#31
1$
1#
b01 "
1!
#32
0#
b01 %
#33
1#
b10 "
#34
0#
#35
b11 "
1#
#36
0#
#37
1#
b01 "
0$
0!
#38
0#
#39
1$
1#
1!
